scrapers/__init__.py
scrapers/cli.py
scrapers/diy.py
scrapers/eu_trans.py
scrapers/publish.py
scrapers/utils.py
tests/__init__.py
tests/conftest.py
tests/test_diy.py
tests/test_eu_trans.py
tests/test_publish.py
arkindex_scrapers-0.2.0.dist-info/METADATA
arkindex_scrapers-0.2.0.dist-info/WHEEL
arkindex_scrapers-0.2.0.dist-info/entry_points.txt
arkindex_scrapers-0.2.0.dist-info/top_level.txt
arkindex_scrapers-0.2.0.dist-info/RECORD
