Metadata-Version: 2.4
Name: arkindex-scrapers
Version: 0.2.0
Summary: Website scrapers to retrieve HTR training datasets.
Author-email: Teklia <contact@teklia.com>
License: AGPL-3.0
Classifier: License :: OSI Approved :: GNU Affero General Public License v3
Requires-Python: >=3.10
Requires-Dist: arkindex-client==1.0.12
Requires-Dist: beautifulsoup4==4.12.2
Requires-Dist: python-dateutil==2.8.2
Requires-Dist: requests==2.28.1
Requires-Dist: teklia-toolbox==0.1.3
Requires-Dist: tenacity==8.2.3
Requires-Dist: tqdm==4.66.1
